LCExtract/LCExtract.py
LCExtract/PanSTARRS.py
LCExtract/__init__.py
LCExtract/config.py
LCExtract/coord.py
LCExtract/dataretrieve.py
LCExtract/entry.py
LCExtract/utilities.py
SDSSRefs/__init__.py
SDSSRefs/config.py
SDSSRefs/controller.py
LCExtract-0.1.8.dist-info/LICENSE
LCExtract-0.1.8.dist-info/METADATA
LCExtract-0.1.8.dist-info/WHEEL
LCExtract-0.1.8.dist-info/top_level.txt
LCExtract-0.1.8.dist-info/RECORD
