Metadata-Version: 2.1
Name: LCExtract
Version: 0.1.8
Summary: Small app to retrieve astronomical object photometry over time (lightcurve)
Home-page: https://github.com/Pommers/LCExtract
Author: Richard Pomeroy
Author-email: RTPomeroy@uclan.ac.uk
License: UNKNOWN
Project-URL: Bug Tracker, https://github.com/Pommers/LCExtract/issues
Platform: UNKNOWN
Classifier: Programming Language :: Python :: 3
Classifier: License :: OSI Approved :: MIT License
Classifier: Operating System :: OS Independent
Requires-Python: >=3.6
